{"dep_prios": [10, 5, 5, 30, 30], "size": 1130, "path": "/home/akshit/django/blogproject/mysite/venv/local/lib/mypy/typeshed/stdlib/3/collections/abc.pyi", "child_modules": [], "mtime": 1537370098, "ignore_all": false, "dependencies": ["sys", "collections", "builtins", "abc", "typing"], "dep_lines": [4, 7, 1, 1, 1], "id": "collections.abc", "suppressed": [], "hash": "af02724cb6b8eac17e9c71e595dc622b", "options": {"strict_optional": false, "disallow_any_expr": false, "disallow_any_generics": false, "disallow_untyped_decorators": false, "follow_imports": "normal", "disallow_any_decorated": false, "quick_and_dirty": false, "warn_no_return": true, "warn_unused_ignores": false, "strict_boolean": false, "always_true": [], "no_implicit_optional": false, "disallow_untyped_calls": false, "ignore_errors": false, "follow_imports_for_stubs": false, "cache_fine_grained": false, "platform": "linux", "show_none_errors": true, "disallow_subclassing_any": false, "disallow_any_explicit": false, "always_false": [], "ignore_missing_imports": false, "check_untyped_defs": false, "warn_return_any": false, "disallow_any_unimported": false, "strict_optional_whitelist": null, "disallow_untyped_defs": false}, "interface_hash": "c636750fa6a3c6613dcdd7386a345296", "version_id": "0.590", "data_mtime": 1537370591}
